Metadata-Version: 1.1
Name: Flask-Redtask
Version: 0.1
Summary: Redqueue integration for flask
Home-page: http://github.com/muromec/flask-redtask
Author: Ilya Petrov
Author-email: ilya.muromec@gmail.com
License: BSD
Platform: any
Classifier: Development Status :: 4 - Beta
Classifier: Environment :: Web Environment
Classifier: Intended Audience :: Developers
Classifier: License :: OSI Approved :: BSD License
Classifier: Operating System :: OS Independent
Classifier: Programming Language :: Python
Classifier: Topic :: Internet :: WWW/HTTP :: Dynamic Content
Classifier: Topic :: Software Development :: Libraries :: Python Modules
